[
  {
    "person": "person_2",
    "task": "Buy groceries",
    "source_text": "",
    "deadline": "tomorrow",
    "status": "open",
    "created_at": 1783773127.420796
  },
  {
    "person": "person_2",
    "task": "Buy milk",
    "source_text": "I will buy Milk Tommorow",
    "deadline": "tomorrow",
    "status": "open",
    "created_at": 1783797837.3395355
  },
  {
    "person": "person_2",
    "task": "Prepare for the Cyntexa Company",
    "source_text": "I have to prepare for the Cyntexa Company",
    "deadline": null,
    "status": "open",
    "created_at": 1783798231.1842685
  }
]